a_pandas_ex_numexpr/LICENSE
a_pandas_ex_numexpr/README.MD
a_pandas_ex_numexpr/__init__.py
a_pandas_ex_numexpr/requirements.txt
a_pandas_ex_numexpr/thirdparty.json
a_pandas_ex_numexpr-0.10.dist-info/LICENSE.rst
a_pandas_ex_numexpr-0.10.dist-info/METADATA
a_pandas_ex_numexpr-0.10.dist-info/WHEEL
a_pandas_ex_numexpr-0.10.dist-info/top_level.txt
a_pandas_ex_numexpr-0.10.dist-info/RECORD
