Metadata-Version: 2.1
Name: a-pandas-ex-numexpr
Version: 0.10
Summary: Pandas DataFrame/Series operations 8 times faster (or even more)
Home-page: https://github.com/hansalemaos/a_pandas_ex_numexpr
Author: Johannes Fischer
Author-email: <aulasparticularesdealemaosp@gmail.com>
License: MIT
Keywords: numexpr,numpy,sort,pandas,series
Classifier: Development Status :: 4 - Beta
Classifier: Programming Language :: Python :: 3 :: Only
Classifier: Programming Language :: Python :: 3.9
Classifier: Topic :: Scientific/Engineering :: Visualization
Classifier: Topic :: Software Development :: Libraries :: Python Modules
Classifier: Topic :: Text Editors :: Text Processing
Classifier: Topic :: Text Processing :: General
Classifier: Topic :: Text Processing :: Indexing
Classifier: Topic :: Text Processing :: Filters
Classifier: Topic :: Utilities
License-File: LICENSE.rst
Requires-Dist: numexpr
Requires-Dist: numpy
Requires-Dist: pandas
Requires-Dist: tolerant-isinstance
